rtl/d.v
module dff (input d, output reg q, input clk, output reg q_bar);
     always @(posedge clk) begin
        
        q <= d;
        q_bar <= ~d;

     end

    
endmodule

tb/d_tb.v
`timescale 1ns/1ps

module dff_tb;

    reg d, clk;
    wire q, q_bar;

    dff uut (
        .d(d),
        .clk(clk),
        .q(q),
        .q_bar(q_bar)
    );

    always #5 clk = ~clk;

    initial begin
        $dumpfile("dff.vcd");
        $dumpvars(0, dff_tb);

        // truth table header
        $display("Time\tclk\td\tq\tq_bar");
        $monitor("%0t\t%b\t%b\t%b\t%b", $time, clk, d, q, q_bar);

        clk = 0;
        d   = 0;

        #7  d = 1;
        #10 d = 0;
        #12 d = 1;
        #10 d = 0;
        #20 d = 1;

        #30 $finish;
    end

endmodule

dff.vcd
$date
	Thu Sep 10 12:37:00 2026
$end
$version
	Icarus Verilog
$end
$timescale
	1ps
$end
$scope module dff_tb $end
$var wire 1 ! q_bar $end
$var wire 1 " q $end
$var reg 1 # clk $end
$var reg 1 $ d $end
$scope module uut $end
$var wire 1 # clk $end
$var wire 1 $ d $end
$var reg 1 " q $end
$var reg 1 ! q_bar $end
$upscope $end
$upscope $end
$enddefinitions $end
#0
$dumpvars
0$
0#
x"
x!
$end
#5000
1!
0"
1#
#7000
1$
#10000
0#
#15000
0!
1"
1#
#17000
0$
#20000
0#
#25000
1!
0"
1#
#29000
1$
#30000
0#
#35000
0!
1"
1#
#39000
0$
#40000
0#
#45000
1!
0"
1#
#50000
0#
#55000
1#
#59000
1$
#60000
0#
#65000
0!
1"
1#
