rtl/jk.v
module jkff (
    input  j,
    input  k,
    input  clk,
    output reg q,
    output reg q_bar
);

    reg next_q;

    always @(*) begin
        case ({j, k})
            2'b00: next_q = q;
            2'b01: next_q = 1'b0;
            2'b10: next_q = 1'b1;
            2'b11: next_q = ~q;
        endcase
    end

    always @(posedge clk) begin
        q     <= next_q;
        q_bar <= ~next_q;
    end

endmodule

tb/jk_tb.v
`timescale 1ns/1ps

module jkff_tb;

    reg j, k, clk;
    wire q, q_bar;

    jkff uut (
        .j(j),
        .k(k),
        .clk(clk),
        .q(q),
        .q_bar(q_bar)
    );

    always #5 clk = ~clk;

    initial begin
        $dumpfile("jkff.vcd");
        $dumpvars(0, jkff_tb);

        $display("Time\tclk\tj\tk\tq\tq_bar");
        $monitor("%0t\t%b\t%b\t%b\t%b\t%b", $time, clk, j, k, q, q_bar);

        clk = 0;
        {j, k} = 2'b00;

        #10 {j, k} = 2'b10;   // set
        #10 {j, k} = 2'b01;   // reset
        #10 {j, k} = 2'b11;   // toggle
        #10 {j, k} = 2'b11;   // toggle again
        #10 {j, k} = 2'b00;   // hold

        #20 $finish;
    end

endmodule

jkff.vcd
$date
	Thu Sep 10 12:35:11 2026
$end
$version
	Icarus Verilog
$end
$timescale
	1ps
$end
$scope module jkff_tb $end
$var wire 1 ! q_bar $end
$var wire 1 " q $end
$var reg 1 # clk $end
$var reg 1 $ j $end
$var reg 1 % k $end
$scope module uut $end
$var wire 1 # clk $end
$var wire 1 $ j $end
$var wire 1 % k $end
$var reg 1 & next_q $end
$var reg 1 " q $end
$var reg 1 ! q_bar $end
$upscope $end
$upscope $end
$enddefinitions $end
#0
$dumpvars
x&
0%
0$
0#
x"
x!
$end
#5000
1#
#10000
1&
0#
1$
#15000
0!
1"
1#
#20000
0&
0#
0$
1%
#25000
1!
0"
1#
#30000
1&
0#
1$
#35000
0&
0!
1"
1#
#40000
0#
#45000
1&
1!
0"
1#
#50000
0&
0#
0$
0%
